nonebot_plugin_random_reply/__init__.py
nonebot_plugin_random_reply/balance.py
nonebot_plugin_random_reply/config.py
nonebot_plugin_random_reply-0.5.4.dist-info/METADATA
nonebot_plugin_random_reply-0.5.4.dist-info/WHEEL
nonebot_plugin_random_reply-0.5.4.dist-info/RECORD
