Metadata-Version: 2.1
Name: nonebot-plugin-random-reply
Version: 0.5.4
Summary: 随机攻击群友插件
License: MIT
Author: Alpaca
Author-email: 202396298@qq.com
Requires-Python: >=3.8,<4.0
Classifier: License :: OSI Approved :: MIT License
Classifier: Programming Language :: Python :: 3
Classifier: Programming Language :: Python :: 3.8
Classifier: Programming Language :: Python :: 3.9
Classifier: Programming Language :: Python :: 3.10
Classifier: Programming Language :: Python :: 3.11
Classifier: Programming Language :: Python :: 3.12
Requires-Dist: nonebot-adapter-onebot (>=2.2.1,<3.0.0)
Requires-Dist: nonebot-plugin-send-anything-anywhere (>=0.7.1)
Requires-Dist: nonebot2 (>=2.2.0,<3.0.0)
Requires-Dist: nonebot_plugin_userinfo (>=0.2.6)
Requires-Dist: openai (>=1.55.3)
